ytpb/__init__.py
ytpb/__main__.py
ytpb/_version.py
ytpb/api.py
ytpb/cache.py
ytpb/download.py
ytpb/errors.py
ytpb/fetchers.py
ytpb/format_spec.py
ytpb/info.py
ytpb/locate.py
ytpb/merge.py
ytpb/playback.py
ytpb/representations.py
ytpb/segment.py
ytpb/streams.py
ytpb/types.py
ytpb/actions/__init__.py
ytpb/actions/capture.py
ytpb/actions/compose.py
ytpb/actions/download.py
ytpb/cli/__init__.py
ytpb/cli/common.py
ytpb/cli/config.py
ytpb/cli/formats.py
ytpb/cli/options.py
ytpb/cli/parameters.py
ytpb/cli/templating.py
ytpb/cli/commands/__init__.py
ytpb/cli/commands/capture.py
ytpb/cli/commands/download.py
ytpb/cli/commands/mpd.py
ytpb/cli/utils/date.py
ytpb/cli/utils/path.py
ytpb/utils/__init__.py
ytpb/utils/ffmpeg.py
ytpb/utils/other.py
ytpb/utils/remote.py
ytpb/utils/url.py
ytpb-2026.1.18.dist-info/METADATA
ytpb-2026.1.18.dist-info/WHEEL
ytpb-2026.1.18.dist-info/entry_points.txt
ytpb-2026.1.18.dist-info/licenses/LICENSE
ytpb-2026.1.18.dist-info/RECORD
