Metadata-Version: 2.4
Name: ytpb
Version: 2026.1.18
Summary: A playback for YouTube live streams
Project-URL: Source, https://github.com/xymaxim/ytpb
Project-URL: Documentation, https://ytpb.readthedocs.io
Author: Maxim Stolyarchuk
License: MIT License
License-File: LICENSE
Keywords: youtube
Classifier: Development Status :: 4 - Beta
Classifier: Environment :: Console
Classifier: Programming Language :: Python
Classifier: Programming Language :: Python :: 3.12
Requires-Python: >=3.12
Requires-Dist: av>=12.0.0
Requires-Dist: click>=8.1.7
Requires-Dist: cloup>=3.0.5
Requires-Dist: jinja2>=3.1.4
Requires-Dist: lark>=1.1.9
Requires-Dist: lxml>=5.2.2
Requires-Dist: pathvalidate>=3.2.0
Requires-Dist: pillow>=10.3.0
Requires-Dist: platformdirs>=4.2.2
Requires-Dist: pycond>=20230212
Requires-Dist: python-mpv-jsonipc>=1.2.0
Requires-Dist: requests>=2.32.0
Requires-Dist: rich>=13.7.0
Requires-Dist: structlog>=24.2.0
Requires-Dist: timedelta-isoformat>=0.6.2.11
Requires-Dist: unidecode>=1.3.8
Requires-Dist: yt-dlp>=2025.12.8
Provides-Extra: dev
Requires-Dist: freezegun>=1.5.1; extra == 'dev'
Requires-Dist: pre-commit; extra == 'dev'
Requires-Dist: pytest-matcher==2.0.1; extra == 'dev'
Requires-Dist: pytest-socket>=0.7.0; extra == 'dev'
Requires-Dist: pytest>=8.2.1; extra == 'dev'
Requires-Dist: responses>=0.25.0; extra == 'dev'
Requires-Dist: toml>=0.10.2; extra == 'dev'
Provides-Extra: docs
Requires-Dist: myst-parser==3.0.1; extra == 'docs'
Requires-Dist: sphinx-toolbox==3.5.0; extra == 'docs'
Requires-Dist: sphinx==7.3.7; extra == 'docs'
Provides-Extra: test
Requires-Dist: freezegun>=1.5.1; extra == 'test'
Requires-Dist: pytest-matcher==2.0.1; extra == 'test'
Requires-Dist: pytest-socket>=0.7.0; extra == 'test'
Requires-Dist: pytest>=8.2.1; extra == 'test'
Requires-Dist: responses>=0.25.0; extra == 'test'
Requires-Dist: toml>=0.10.2; extra == 'test'
